torcheasy/__init__.py
torcheasy/config.py
torcheasy/trainable.py
torcheasy-0.1.2.dist-info/METADATA
torcheasy-0.1.2.dist-info/WHEEL
torcheasy-0.1.2.dist-info/top_level.txt
torcheasy-0.1.2.dist-info/RECORD
