Metadata-Version: 2.1
Name: torcheasy
Version: 0.1.2
Summary: Easily training module for PyTorch.
Home-page: https://github.com/fuen1590/Torcheasy
Author: En Fu
Author-email: fuensit@qq.com
Classifier: Programming Language :: Python :: 3
Classifier: License :: OSI Approved :: MIT License
Requires-Python: ~=3.6
Requires-Dist: torch >=1.5.0
Requires-Dist: numpy >=1.21.2
Requires-Dist: scipy >=1.5.2
Requires-Dist: matplotlib >=3.4.2
